FitBridge/__init__.py
FitBridge/main.py
FitBridge-0.4.dist-info/LICENSE
FitBridge-0.4.dist-info/METADATA
FitBridge-0.4.dist-info/WHEEL
FitBridge-0.4.dist-info/entry_points.txt
FitBridge-0.4.dist-info/top_level.txt
FitBridge-0.4.dist-info/RECORD
