Metadata-Version: 2.1
Name: FitBridge
Version: 0.4
Summary: A simple script to sync Gadgetbridge exported data to Google Fit
Home-page: https://github.com/moh53n/FitBridge
Author: Mohsen Tahmasebi
Author-email: moh53n@moh53n.ir
License: GPLv3
Project-URL: Bug Tracker, https://github.com/moh53n/FitBridge/issues
Classifier: Programming Language :: Python :: 3
Classifier: License :: OSI Approved :: GNU General Public License v3 (GPLv3)
Requires-Python: >=3.8
License-File: LICENSE
Requires-Dist: requests
Requires-Dist: google-auth-oauthlib ==0.4.1
Requires-Dist: google-api-python-client
Requires-Dist: appdirs
